{"frames": {

"RaceCar":
{
	"frame": {"x":0,"y":0,"w":12,"h":20},
	"rotated": false,
	"trimmed": false,
	"spriteSourceSize": {"x":0,"y":0,"w":12,"h":20},
	"sourceSize": {"w":12,"h":20}
}},
"meta": {
	"app": "http://www.codeandweb.com/texturepacker ",
	"version": "1.0",
	"image": "entities0.png",
	"format": "RGBA8888",
	"size": {"w":16,"h":32},
	"scale": "1",
	"smartupdate": "$TexturePacker:SmartUpdate:2e9c51d828bf2e8b17793cc551797e3e:11762a9ba627b6cc07763616616bd077:14f9d32ba27a06d451a9f418c7a01db0$"
}
}
